{
	"configurations" : 
	[
		{
			"directories" : 
			[
				{
					"build" : ".",
					"childIndexes" : 
					[
						1,
						2
					],
					"hasInstallRule" : true,
					"jsonFile" : "directory-.-dfa6fbb634c667682575.json",
					"minimumCMakeVersion" : 
					{
						"string" : "3.12"
					},
					"projectIndex" : 0,
					"source" : ".",
					"targetIndexes" : 
					[
						2,
						4
					]
				},
				{
					"build" : "doc/doxygen",
					"jsonFile" : "directory-doc.doxygen-afcdf6447251a25b7b9c.json",
					"minimumCMakeVersion" : 
					{
						"string" : "3.16.3"
					},
					"parentIndex" : 0,
					"projectIndex" : 0,
					"source" : "doc/doxygen"
				},
				{
					"build" : "test",
					"childIndexes" : 
					[
						3
					],
					"jsonFile" : "directory-test-451c0598f41488bb20b9.json",
					"minimumCMakeVersion" : 
					{
						"string" : "3.16.3"
					},
					"parentIndex" : 0,
					"projectIndex" : 0,
					"source" : "test",
					"targetIndexes" : 
					[
						3
					]
				},
				{
					"build" : "gtest",
					"jsonFile" : "directory-gtest-a2408fe1a73b92c5e636.json",
					"minimumCMakeVersion" : 
					{
						"string" : "3.8"
					},
					"parentIndex" : 2,
					"projectIndex" : 1,
					"source" : "/opt/ros/humble/src/gtest_vendor",
					"targetIndexes" : 
					[
						0,
						1
					]
				}
			],
			"name" : "",
			"projects" : 
			[
				{
					"childIndexes" : 
					[
						1
					],
					"directoryIndexes" : 
					[
						0,
						1,
						2
					],
					"name" : "kindr",
					"targetIndexes" : 
					[
						2,
						3,
						4
					]
				},
				{
					"directoryIndexes" : 
					[
						3
					],
					"name" : "gtest",
					"parentIndex" : 0,
					"targetIndexes" : 
					[
						0,
						1
					]
				}
			],
			"targets" : 
			[
				{
					"directoryIndex" : 3,
					"id" : "gtest::@0af4add9fe94340e763e",
					"jsonFile" : "target-gtest-5b63979db20ce6450eba.json",
					"name" : "gtest",
					"projectIndex" : 1
				},
				{
					"directoryIndex" : 3,
					"id" : "gtest_main::@0af4add9fe94340e763e",
					"jsonFile" : "target-gtest_main-87335446aa5480775628.json",
					"name" : "gtest_main",
					"projectIndex" : 1
				},
				{
					"directoryIndex" : 0,
					"id" : "kindr_uninstall::@6890427a1f51a3e7e1df",
					"jsonFile" : "target-kindr_uninstall-e04a07b65d52e43df575.json",
					"name" : "kindr_uninstall",
					"projectIndex" : 0
				},
				{
					"directoryIndex" : 2,
					"id" : "test_kindr::@36f028580bb02cc8272a",
					"jsonFile" : "target-test_kindr-9d123bc68f8f16683481.json",
					"name" : "test_kindr",
					"projectIndex" : 0
				},
				{
					"directoryIndex" : 0,
					"id" : "uninstall::@6890427a1f51a3e7e1df",
					"jsonFile" : "target-uninstall-8a75416bae8d63fefb57.json",
					"name" : "uninstall",
					"projectIndex" : 0
				}
			]
		}
	],
	"kind" : "codemodel",
	"paths" : 
	{
		"build" : "/root/Lunar_ROADSTER/lr_ws/build/kindr",
		"source" : "/root/Lunar_ROADSTER/lr_ws/src/drivers/kindr"
	},
	"version" : 
	{
		"major" : 2,
		"minor" : 4
	}
}
